{
    "organizations": {
        "totalCount": 2,
        "nodes": [
            {
                "login": "DevTips",
                "avatarURL": "https://avatars2.githubusercontent.com/u/7217478?v=3",
                "url": "https://github.com/DevTips",
                "name": "DevTips"
            },
            {
                "login": "Exposify",
                "avatarURL": "https://avatars1.githubusercontent.com/u/19746775?v=3",
                "url": "https://github.com/Exposify",
                "name": "Exposify"
            }
        ]
    },
    "location": "Germany",
    "email": "",
    "pullRequests": {
        "totalCount": 15
    },
    "company": "@Exposify",
    "pinnedRepositories": {
        "totalCount": 4,
        "nodes": [
            {
                "name": "code-guide"
            },
            {
                "name": "boilerplate"
            },
            {
                "name": "laravel-pdf"
            },
            {
                "name": "grunt-sync-deploy"
            }
        ]
    },
    "websiteURL": "instagram.com/niklasravnsborg",
    "watching": {
        "totalCount": 21
    },
    "avatarURL": "https://avatars1.githubusercontent.com/u/6717303?v=3",
    "starredRepositories": {
        "totalCount": 28
    },
    "followers": {
        "totalCount": 195
    },
    "login": "niklasravnsborg",
    "following": {
        "totalCount": 11
    },
    "contributedRepositories": {
        "totalCount": 17,
        "edges": [
            {
                "node": {
                    "description": ":tada: www.exposify.de",
                    "forks": {
                        "totalCount": 0
                    },
                    "id": "MDEwOlJlcG9zaXRvcnk1MDQ0NDA1Mw==",
                    "languages": {
                        "edges": [
                            {
                                "node": {
                                    "color": "#563d7c",
                                    "id": "MDg6TGFuZ3VhZ2UzMDg=",
                                    "name": "CSS"
                                },
                                "size": 23100
                            },
                            {
                                "node": {
                                    "color": "#e44b23",
                                    "id": "MDg6TGFuZ3VhZ2U0MTc=",
                                    "name": "HTML"
                                },
                                "size": 16772
                            },
                            {
                                "node": {
                                    "color": "#f1e05a",
                                    "id": "MDg6TGFuZ3VhZ2UxNDA=",
                                    "name": "JavaScript"
                                },
                                "size": 9897
                            },
                            {
                                "node": {
                                    "color": "#4F5D95",
                                    "id": "MDg6TGFuZ3VhZ2UxNTE=",
                                    "name": "PHP"
                                },
                                "size": 7380
                            }
                        ]
                    },
                    "primaryLanguage": {
                        "color": "#563d7c",
                        "name": "CSS",
                        "id": "MDg6TGFuZ3VhZ2UzMDg="
                    },
                    "updatedAt": "2016-11-29T17:05:36Z",
                    "watchers": {
                        "totalCount": 2
                    },
                    "stargazers": {
                        "totalCount": 1
                    },
                    "isFork": false,
                    "contribution": {
                        "adds": 29967,
                        "total_commits": 104,
                        "num_of_weeks": 24,
                        "dels": 27433
                    },
                    "homepageURL": "",
                    "createdAt": "2016-01-26T16:57:33Z",
                    "name": "exposify-website"
                }
            },
            {
                "node": {
                    "description": ":office: www.bakirimmobilien.de",
                    "forks": {
                        "totalCount": 0
                    },
                    "id": "MDEwOlJlcG9zaXRvcnkzMTQ2MTEzNw==",
                    "languages": {
                        "edges": [
                            {
                                "node": {
                                    "color": "#701516",
                                    "id": "MDg6TGFuZ3VhZ2UxNDE=",
                                    "name": "Ruby"
                                },
                                "size": 60
                            },
                            {
                                "node": {
                                    "color": "#e44b23",
                                    "id": "MDg6TGFuZ3VhZ2U0MTc=",
                                    "name": "HTML"
                                },
                                "size": 19906
                            },
                            {
                                "node": {
                                    "color": "#f1e05a",
                                    "id": "MDg6TGFuZ3VhZ2UxNDA=",
                                    "name": "JavaScript"
                                },
                                "size": 2067
                            },
                            {
                                "node": {
                                    "color": "#4F5D95",
                                    "id": "MDg6TGFuZ3VhZ2UxNTE=",
                                    "name": "PHP"
                                },
                                "size": 1668
                            },
                            {
                                "node": {
                                    "color": null,
                                    "id": "MDg6TGFuZ3VhZ2U0MTg=",
                                    "name": "ApacheConf"
                                },
                                "size": 1701
                            },
                            {
                                "node": {
                                    "color": "#563d7c",
                                    "id": "MDg6TGFuZ3VhZ2UzMDg=",
                                    "name": "CSS"
                                },
                                "size": 37318
                            }
                        ]
                    },
                    "primaryLanguage": {
                        "color": "#563d7c",
                        "name": "CSS",
                        "id": "MDg6TGFuZ3VhZ2UzMDg="
                    },
                    "updatedAt": "2016-11-12T09:37:16Z",
                    "watchers": {
                        "totalCount": 2
                    },
                    "stargazers": {
                        "totalCount": 0
                    },
                    "isFork": false,
                    "contribution": {
                        "adds": 50610,
                        "total_commits": 200,
                        "num_of_weeks": 64,
                        "dels": 26319
                    },
                    "homepageURL": "",
                    "createdAt": "2015-02-28T11:50:12Z",
                    "name": "bakirimmobilien_de"
                }
            },
            {
                "node": {
                    "description": " :page_facing_up: Easily generate PDF documents from HTML inside of Laravel 5.",
                    "forks": {
                        "totalCount": 10
                    },
                    "id": "MDEwOlJlcG9zaXRvcnk1NjQ5MTM2NQ==",
                    "languages": {
                        "edges": [
                            {
                                "node": {
                                    "color": "#4F5D95",
                                    "id": "MDg6TGFuZ3VhZ2UxNTE=",
                                    "name": "PHP"
                                },
                                "size": 6694
                            }
                        ]
                    },
                    "primaryLanguage": {
                        "color": "#4F5D95",
                        "name": "PHP",
                        "id": "MDg6TGFuZ3VhZ2UxNTE="
                    },
                    "updatedAt": "2017-01-30T18:30:14Z",
                    "watchers": {
                        "totalCount": 4
                    },
                    "stargazers": {
                        "totalCount": 12
                    },
                    "isFork": false,
                    "contribution": {
                        "adds": 925,
                        "total_commits": 20,
                        "num_of_weeks": 6,
                        "dels": 509
                    },
                    "homepageURL": "",
                    "createdAt": "2016-04-18T08:41:25Z",
                    "name": "laravel-pdf"
                }
            },
            {
                "node": {
                    "description": null,
                    "forks": {
                        "totalCount": 0
                    },
                    "id": "MDEwOlJlcG9zaXRvcnk1MzgxMDA0NQ==",
                    "languages": {
                        "edges": [
                            {
                                "node": {
                                    "color": "#4F5D95",
                                    "id": "MDg6TGFuZ3VhZ2UxNTE=",
                                    "name": "PHP"
                                },
                                "size": 76641
                            },
                            {
                                "node": {
                                    "color": null,
                                    "id": "MDg6TGFuZ3VhZ2U0MTg=",
                                    "name": "ApacheConf"
                                },
                                "size": 768
                            },
                            {
                                "node": {
                                    "color": "#563d7c",
                                    "id": "MDg6TGFuZ3VhZ2UzMDg=",
                                    "name": "CSS"
                                },
                                "size": 19048
                            },
                            {
                                "node": {
                                    "color": "#f1e05a",
                                    "id": "MDg6TGFuZ3VhZ2UxNDA=",
                                    "name": "JavaScript"
                                },
                                "size": 961
                            }
                        ]
                    },
                    "primaryLanguage": {
                        "color": "#4F5D95",
                        "name": "PHP",
                        "id": "MDg6TGFuZ3VhZ2UxNTE="
                    },
                    "updatedAt": "2016-03-13T22:08:18Z",
                    "watchers": {
                        "totalCount": 2
                    },
                    "stargazers": {
                        "totalCount": 0
                    },
                    "isFork": false,
                    "contribution": {
                        "adds": 3818,
                        "total_commits": 15,
                        "num_of_weeks": 3,
                        "dels": 293
                    },
                    "homepageURL": null,
                    "createdAt": "2016-03-13T22:02:31Z",
                    "name": "exposify-feature-vote"
                }
            },
            {
                "node": {
                    "description": ":computer: Dynamic H5BP using Grunt, Jade, Sass and a Jekyll inspired page compilation.",
                    "forks": {
                        "totalCount": 0
                    },
                    "id": "MDEwOlJlcG9zaXRvcnkzMzI2ODM1NQ==",
                    "languages": {
                        "edges": [
                            {
                                "node": {
                                    "color": "#e44b23",
                                    "id": "MDg6TGFuZ3VhZ2U0MTc=",
                                    "name": "HTML"
                                },
                                "size": 1987
                            },
                            {
                                "node": {
                                    "color": "#563d7c",
                                    "id": "MDg6TGFuZ3VhZ2UzMDg=",
                                    "name": "CSS"
                                },
                                "size": 163
                            },
                            {
                                "node": {
                                    "color": "#f1e05a",
                                    "id": "MDg6TGFuZ3VhZ2UxNDA=",
                                    "name": "JavaScript"
                                },
                                "size": 3810
                            },
                            {
                                "node": {
                                    "color": null,
                                    "id": "MDg6TGFuZ3VhZ2U0MTg=",
                                    "name": "ApacheConf"
                                },
                                "size": 347
                            }
                        ]
                    },
                    "primaryLanguage": {
                        "color": "#f1e05a",
                        "name": "JavaScript",
                        "id": "MDg6TGFuZ3VhZ2UxNDA="
                    },
                    "updatedAt": "2016-10-14T12:56:54Z",
                    "watchers": {
                        "totalCount": 1
                    },
                    "stargazers": {
                        "totalCount": 0
                    },
                    "isFork": false,
                    "contribution": {
                        "adds": 1044,
                        "total_commits": 17,
                        "num_of_weeks": 7,
                        "dels": 268
                    },
                    "homepageURL": "",
                    "createdAt": "2015-04-01T19:35:39Z",
                    "name": "boilerplate"
                }
            },
            {
                "node": {
                    "description": ":vhs: http://videos.niklasravnsborg.com",
                    "forks": {
                        "totalCount": 0
                    },
                    "id": "MDEwOlJlcG9zaXRvcnkzNjk4MTQ3Nw==",
                    "languages": {
                        "edges": [
                            {
                                "node": {
                                    "color": "#f1e05a",
                                    "id": "MDg6TGFuZ3VhZ2UxNDA=",
                                    "name": "JavaScript"
                                },
                                "size": 5714
                            },
                            {
                                "node": {
                                    "color": "#e44b23",
                                    "id": "MDg6TGFuZ3VhZ2U0MTc=",
                                    "name": "HTML"
                                },
                                "size": 3446
                            },
                            {
                                "node": {
                                    "color": "#563d7c",
                                    "id": "MDg6TGFuZ3VhZ2UzMDg=",
                                    "name": "CSS"
                                },
                                "size": 2129
                            },
                            {
                                "node": {
                                    "color": null,
                                    "id": "MDg6TGFuZ3VhZ2U0MTg=",
                                    "name": "ApacheConf"
                                },
                                "size": 141
                            }
                        ]
                    },
                    "primaryLanguage": {
                        "color": "#f1e05a",
                        "name": "JavaScript",
                        "id": "MDg6TGFuZ3VhZ2UxNDA="
                    },
                    "updatedAt": "2016-12-09T17:23:18Z",
                    "watchers": {
                        "totalCount": 1
                    },
                    "stargazers": {
                        "totalCount": 0
                    },
                    "isFork": false,
                    "contribution": {
                        "adds": 1437,
                        "total_commits": 53,
                        "num_of_weeks": 21,
                        "dels": 239
                    },
                    "homepageURL": "",
                    "createdAt": "2015-06-06T13:44:38Z",
                    "name": "niklasravnsborg_videos"
                }
            },
            {
                "node": {
                    "description": "A free Jekyll Theme developed by the DevTips Community",
                    "forks": {
                        "totalCount": 498
                    },
                    "id": "MDEwOlJlcG9zaXRvcnkyMDU4NzU4Nw==",
                    "languages": {
                        "edges": [
                            {
                                "node": {
                                    "color": "#e44b23",
                                    "id": "MDg6TGFuZ3VhZ2U0MTc=",
                                    "name": "HTML"
                                },
                                "size": 14867
                            },
                            {
                                "node": {
                                    "color": "#563d7c",
                                    "id": "MDg6TGFuZ3VhZ2UzMDg=",
                                    "name": "CSS"
                                },
                                "size": 45501
                            },
                            {
                                "node": {
                                    "color": "#f1e05a",
                                    "id": "MDg6TGFuZ3VhZ2UxNDA=",
                                    "name": "JavaScript"
                                },
                                "size": 12134
                            }
                        ]
                    },
                    "primaryLanguage": {
                        "color": "#563d7c",
                        "name": "CSS",
                        "id": "MDg6TGFuZ3VhZ2UzMDg="
                    },
                    "updatedAt": "2017-02-06T00:07:12Z",
                    "watchers": {
                        "totalCount": 273
                    },
                    "stargazers": {
                        "totalCount": 518
                    },
                    "isFork": false,
                    "contribution": -1,
                    "homepageURL": "http://devtips.github.io/Artists-Theme",
                    "createdAt": "2014-06-07T06:59:26Z",
                    "name": "Artists-Theme"
                }
            },
            {
                "node": {
                    "description": ":arrow_up: Incremental deploy changed files to SSH.",
                    "forks": {
                        "totalCount": 1
                    },
                    "id": "MDEwOlJlcG9zaXRvcnkzODk2MTU2MQ==",
                    "languages": {
                        "edges": [
                            {
                                "node": {
                                    "color": "#f1e05a",
                                    "id": "MDg6TGFuZ3VhZ2UxNDA=",
                                    "name": "JavaScript"
                                },
                                "size": 6909
                            }
                        ]
                    },
                    "primaryLanguage": {
                        "color": "#f1e05a",
                        "name": "JavaScript",
                        "id": "MDg6TGFuZ3VhZ2UxNDA="
                    },
                    "updatedAt": "2017-01-25T13:48:02Z",
                    "watchers": {
                        "totalCount": 2
                    },
                    "stargazers": {
                        "totalCount": 1
                    },
                    "isFork": false,
                    "contribution": {
                        "adds": 527,
                        "total_commits": 21,
                        "num_of_weeks": 10,
                        "dels": 91
                    },
                    "homepageURL": "https://www.npmjs.com/package/grunt-sync-deploy",
                    "createdAt": "2015-07-12T12:42:04Z",
                    "name": "grunt-sync-deploy"
                }
            },
            {
                "node": {
                    "description": ":rainbow: Kengumedia Website: www.kengumedia.de",
                    "forks": {
                        "totalCount": 0
                    },
                    "id": "MDEwOlJlcG9zaXRvcnk1MTI2MDU4Nw==",
                    "languages": {
                        "edges": [
                            {
                                "node": {
                                    "color": "#f1e05a",
                                    "id": "MDg6TGFuZ3VhZ2UxNDA=",
                                    "name": "JavaScript"
                                },
                                "size": 3119
                            },
                            {
                                "node": {
                                    "color": null,
                                    "id": "MDg6TGFuZ3VhZ2U0MTg=",
                                    "name": "ApacheConf"
                                },
                                "size": 567
                            },
                            {
                                "node": {
                                    "color": "#e44b23",
                                    "id": "MDg6TGFuZ3VhZ2U0MTc=",
                                    "name": "HTML"
                                },
                                "size": 2937
                            },
                            {
                                "node": {
                                    "color": "#563d7c",
                                    "id": "MDg6TGFuZ3VhZ2UzMDg=",
                                    "name": "CSS"
                                },
                                "size": 2048
                            }
                        ]
                    },
                    "primaryLanguage": {
                        "color": "#f1e05a",
                        "name": "JavaScript",
                        "id": "MDg6TGFuZ3VhZ2UxNDA="
                    },
                    "updatedAt": "2016-12-25T13:09:42Z",
                    "watchers": {
                        "totalCount": 1
                    },
                    "stargazers": {
                        "totalCount": 0
                    },
                    "isFork": false,
                    "contribution": {
                        "adds": 837,
                        "total_commits": 6,
                        "num_of_weeks": 4,
                        "dels": 7
                    },
                    "homepageURL": "",
                    "createdAt": "2016-02-07T18:57:10Z",
                    "name": "kengumedia-website"
                }
            },
            {
                "node": {
                    "description": "Exposify PHP Library",
                    "forks": {
                        "totalCount": 0
                    },
                    "id": "MDEwOlJlcG9zaXRvcnk3NTExMzQxOQ==",
                    "languages": {
                        "edges": [
                            {
                                "node": {
                                    "color": "#4F5D95",
                                    "id": "MDg6TGFuZ3VhZ2UxNTE=",
                                    "name": "PHP"
                                },
                                "size": 3878
                            }
                        ]
                    },
                    "primaryLanguage": {
                        "color": "#4F5D95",
                        "name": "PHP",
                        "id": "MDg6TGFuZ3VhZ2UxNTE="
                    },
                    "updatedAt": "2016-12-22T19:17:24Z",
                    "watchers": {
                        "totalCount": 2
                    },
                    "stargazers": {
                        "totalCount": 2
                    },
                    "isFork": false,
                    "contribution": -1,
                    "homepageURL": "",
                    "createdAt": "2016-11-29T19:13:32Z",
                    "name": "exposify-php"
                }
            },
            {
                "node": {
                    "description": "https://helpdocs.exposify.de/",
                    "forks": {
                        "totalCount": 0
                    },
                    "id": "MDEwOlJlcG9zaXRvcnk2MjM5MjI5Ng==",
                    "languages": {
                        "edges": []
                    },
                    "primaryLanguage": null,
                    "updatedAt": "2016-11-29T19:32:20Z",
                    "watchers": {
                        "totalCount": 1
                    },
                    "stargazers": {
                        "totalCount": 0
                    },
                    "isFork": false,
                    "contribution": -1,
                    "homepageURL": "",
                    "createdAt": "2016-07-01T12:43:43Z",
                    "name": "Dokumentation"
                }
            },
            {
                "node": {
                    "description": null,
                    "forks": {
                        "totalCount": 0
                    },
                    "id": "MDEwOlJlcG9zaXRvcnk2MzA2NTU0Nw==",
                    "languages": {
                        "edges": [
                            {
                                "node": {
                                    "color": "#f1e05a",
                                    "id": "MDg6TGFuZ3VhZ2UxNDA=",
                                    "name": "JavaScript"
                                },
                                "size": 2996
                            },
                            {
                                "node": {
                                    "color": "#563d7c",
                                    "id": "MDg6TGFuZ3VhZ2UzMDg=",
                                    "name": "CSS"
                                },
                                "size": 119
                            }
                        ]
                    },
                    "primaryLanguage": {
                        "color": "#f1e05a",
                        "name": "JavaScript",
                        "id": "MDg6TGFuZ3VhZ2UxNDA="
                    },
                    "updatedAt": "2016-09-02T23:37:22Z",
                    "watchers": {
                        "totalCount": 1
                    },
                    "stargazers": {
                        "totalCount": 1
                    },
                    "isFork": false,
                    "contribution": {
                        "adds": 127,
                        "total_commits": 1,
                        "num_of_weeks": 1,
                        "dels": 0
                    },
                    "homepageURL": null,
                    "createdAt": "2016-07-11T12:23:06Z",
                    "name": "N1-Auto-Recipients"
                }
            },
            {
                "node": {
                    "description": ":green_heart: www.bakirbrader.de",
                    "forks": {
                        "totalCount": 0
                    },
                    "id": "MDEwOlJlcG9zaXRvcnkzMTQ2MTcyNg==",
                    "languages": {
                        "edges": [
                            {
                                "node": {
                                    "color": "#f1e05a",
                                    "id": "MDg6TGFuZ3VhZ2UxNDA=",
                                    "name": "JavaScript"
                                },
                                "size": 4017
                            },
                            {
                                "node": {
                                    "color": "#e44b23",
                                    "id": "MDg6TGFuZ3VhZ2U0MTc=",
                                    "name": "HTML"
                                },
                                "size": 8894
                            },
                            {
                                "node": {
                                    "color": "#563d7c",
                                    "id": "MDg6TGFuZ3VhZ2UzMDg=",
                                    "name": "CSS"
                                },
                                "size": 12370
                            },
                            {
                                "node": {
                                    "color": null,
                                    "id": "MDg6TGFuZ3VhZ2U0MTg=",
                                    "name": "ApacheConf"
                                },
                                "size": 673
                            }
                        ]
                    },
                    "primaryLanguage": {
                        "color": "#563d7c",
                        "name": "CSS",
                        "id": "MDg6TGFuZ3VhZ2UzMDg="
                    },
                    "updatedAt": "2016-03-05T09:04:32Z",
                    "watchers": {
                        "totalCount": 1
                    },
                    "stargazers": {
                        "totalCount": 0
                    },
                    "isFork": false,
                    "contribution": {
                        "adds": 20240,
                        "total_commits": 62,
                        "num_of_weeks": 17,
                        "dels": 1852
                    },
                    "homepageURL": "",
                    "createdAt": "2015-02-28T12:17:31Z",
                    "name": "bakirbrader_de"
                }
            },
            {
                "node": {
                    "description": "\ud83c\udfb7\ud83c\udfb6 www.klangrisotto.de",
                    "forks": {
                        "totalCount": 0
                    },
                    "id": "MDEwOlJlcG9zaXRvcnk3MDkwODU5Mg==",
                    "languages": {
                        "edges": [
                            {
                                "node": {
                                    "color": "#f1e05a",
                                    "id": "MDg6TGFuZ3VhZ2UxNDA=",
                                    "name": "JavaScript"
                                },
                                "size": 3810
                            },
                            {
                                "node": {
                                    "color": null,
                                    "id": "MDg6TGFuZ3VhZ2U0MTg=",
                                    "name": "ApacheConf"
                                },
                                "size": 353
                            },
                            {
                                "node": {
                                    "color": "#e44b23",
                                    "id": "MDg6TGFuZ3VhZ2U0MTc=",
                                    "name": "HTML"
                                },
                                "size": 2733
                            },
                            {
                                "node": {
                                    "color": "#563d7c",
                                    "id": "MDg6TGFuZ3VhZ2UzMDg=",
                                    "name": "CSS"
                                },
                                "size": 1294
                            }
                        ]
                    },
                    "primaryLanguage": {
                        "color": "#f1e05a",
                        "name": "JavaScript",
                        "id": "MDg6TGFuZ3VhZ2UxNDA="
                    },
                    "updatedAt": "2016-10-14T21:29:51Z",
                    "watchers": {
                        "totalCount": 1
                    },
                    "stargazers": {
                        "totalCount": 0
                    },
                    "isFork": false,
                    "contribution": {
                        "adds": 852,
                        "total_commits": 1,
                        "num_of_weeks": 1,
                        "dels": 0
                    },
                    "homepageURL": "",
                    "createdAt": "2016-10-14T12:33:28Z",
                    "name": "klangrisotto-website"
                }
            },
            {
                "node": {
                    "description": ":thumbsup: Trying to define good code. Will be a full stack web development guide, eventually.",
                    "forks": {
                        "totalCount": 2
                    },
                    "id": "MDEwOlJlcG9zaXRvcnk0MDU5Nzc0MA==",
                    "languages": {
                        "edges": []
                    },
                    "primaryLanguage": null,
                    "updatedAt": "2016-11-22T13:19:04Z",
                    "watchers": {
                        "totalCount": 1
                    },
                    "stargazers": {
                        "totalCount": 12
                    },
                    "isFork": false,
                    "contribution": {
                        "adds": 108,
                        "total_commits": 5,
                        "num_of_weeks": 4,
                        "dels": 15
                    },
                    "homepageURL": "",
                    "createdAt": "2015-08-12T11:45:48Z",
                    "name": "code-guide"
                }
            },
            {
                "node": {
                    "description": "mPDF is a PHP library generating PDF files from UTF-8 encoded HTML",
                    "forks": {
                        "totalCount": 200
                    },
                    "id": "MDEwOlJlcG9zaXRvcnkzMTU5NTYwOQ==",
                    "languages": {
                        "edges": [
                            {
                                "node": {
                                    "color": "#4F5D95",
                                    "id": "MDg6TGFuZ3VhZ2UxNTE=",
                                    "name": "PHP"
                                },
                                "size": 3694519
                            },
                            {
                                "node": {
                                    "color": "#563d7c",
                                    "id": "MDg6TGFuZ3VhZ2UzMDg=",
                                    "name": "CSS"
                                },
                                "size": 11232
                            }
                        ]
                    },
                    "primaryLanguage": {
                        "color": "#4F5D95",
                        "name": "PHP",
                        "id": "MDg6TGFuZ3VhZ2UxNTE="
                    },
                    "updatedAt": "2017-02-05T15:04:00Z",
                    "watchers": {
                        "totalCount": 60
                    },
                    "stargazers": {
                        "totalCount": 558
                    },
                    "isFork": false,
                    "contribution": {
                        "adds": 1,
                        "total_commits": 1,
                        "num_of_weeks": 1,
                        "dels": 1
                    },
                    "homepageURL": "https://mpdf.github.io",
                    "createdAt": "2015-03-03T11:44:47Z",
                    "name": "mpdf"
                }
            },
            {
                "node": {
                    "description": null,
                    "forks": {
                        "totalCount": 0
                    },
                    "id": "MDEwOlJlcG9zaXRvcnk1MjYzNTQxNQ==",
                    "languages": {
                        "edges": []
                    },
                    "primaryLanguage": null,
                    "updatedAt": "2016-02-26T21:58:35Z",
                    "watchers": {
                        "totalCount": 1
                    },
                    "stargazers": {
                        "totalCount": 0
                    },
                    "isFork": false,
                    "contribution": -1,
                    "homepageURL": null,
                    "createdAt": "2016-02-26T21:58:35Z",
                    "name": "richartkeil.com"
                }
            }
        ],
        "pageInfo": {
            "hasNextPage": false,
            "endCursor": "MTc="
        }
    },
    "bio": "Maker.",
    "gists": {
        "totalCount": 4
    },
    "name": "Niklas Ravnsborg-Gjertsen",
    "id": "MDQ6VXNlcjY3MTczMDM="
}