{
    "organizations": {
        "totalCount": 0,
        "nodes": []
    },
    "location": "Germany",
    "email": "ping@nok.onl",
    "pullRequests": {
        "totalCount": 46
    },
    "company": "",
    "pinnedRepositories": {
        "totalCount": 6,
        "nodes": [
            {
                "name": "sklearn-porter"
            },
            {
                "name": "weka-porter"
            },
            {
                "name": "onedollar-unistroke-coffee"
            },
            {
                "name": "markdown-toc"
            },
            {
                "name": "leap-motion-processing"
            },
            {
                "name": "myo-processing"
            }
        ]
    },
    "websiteURL": "http://nok.onl",
    "watching": {
        "totalCount": 22
    },
    "avatarURL": "https://avatars2.githubusercontent.com/u/670641?v=3",
    "starredRepositories": {
        "totalCount": 321
    },
    "followers": {
        "totalCount": 92
    },
    "login": "nok",
    "following": {
        "totalCount": 39
    },
    "contributedRepositories": {
        "totalCount": 23,
        "edges": [
            {
                "node": {
                    "description": "Transpile trained scikit-learn models to C, Java, JavaScript and others.",
                    "forks": {
                        "totalCount": 12
                    },
                    "id": "MDEwOlJlcG9zaXRvcnk2MTc1NTMxOA==",
                    "languages": {
                        "edges": [
                            {
                                "node": {
                                    "color": "#89e051",
                                    "id": "MDg6TGFuZ3VhZ2UxMzk=",
                                    "name": "Shell"
                                },
                                "size": 916
                            },
                            {
                                "node": {
                                    "color": "#3572A5",
                                    "id": "MDg6TGFuZ3VhZ2UxNDU=",
                                    "name": "Python"
                                },
                                "size": 123869
                            }
                        ]
                    },
                    "primaryLanguage": {
                        "color": "#3572A5",
                        "name": "Python",
                        "id": "MDg6TGFuZ3VhZ2UxNDU="
                    },
                    "updatedAt": "2017-02-04T10:11:02Z",
                    "watchers": {
                        "totalCount": 3
                    },
                    "stargazers": {
                        "totalCount": 111
                    },
                    "isFork": false,
                    "contribution": {
                        "adds": 51555,
                        "total_commits": 244,
                        "num_of_weeks": 32,
                        "dels": 32670
                    },
                    "homepageURL": "",
                    "createdAt": "2016-06-22T22:21:34Z",
                    "name": "sklearn-porter"
                }
            },
            {
                "node": {
                    "description": "Gamified community server",
                    "forks": {
                        "totalCount": 1
                    },
                    "id": "MDEwOlJlcG9zaXRvcnkzMjUyNTE5MA==",
                    "languages": {
                        "edges": [
                            {
                                "node": {
                                    "color": "#e44b23",
                                    "id": "MDg6TGFuZ3VhZ2U0MTc=",
                                    "name": "HTML"
                                },
                                "size": 203260
                            },
                            {
                                "node": {
                                    "color": "#f1e05a",
                                    "id": "MDg6TGFuZ3VhZ2UxNDA=",
                                    "name": "JavaScript"
                                },
                                "size": 7848
                            },
                            {
                                "node": {
                                    "color": null,
                                    "id": "MDg6TGFuZ3VhZ2U0MTg=",
                                    "name": "ApacheConf"
                                },
                                "size": 553
                            },
                            {
                                "node": {
                                    "color": "#4F5D95",
                                    "id": "MDg6TGFuZ3VhZ2UxNTE=",
                                    "name": "PHP"
                                },
                                "size": 157594
                            }
                        ]
                    },
                    "primaryLanguage": {
                        "color": "#e44b23",
                        "name": "HTML",
                        "id": "MDg6TGFuZ3VhZ2U0MTc="
                    },
                    "updatedAt": "2017-01-10T14:52:52Z",
                    "watchers": {
                        "totalCount": 6
                    },
                    "stargazers": {
                        "totalCount": 0
                    },
                    "isFork": false,
                    "contribution": -1,
                    "homepageURL": "https://bubbles.gpii.eu",
                    "createdAt": "2015-03-19T14:08:55Z",
                    "name": "Bubbles"
                }
            },
            {
                "node": {
                    "description": "Rebuild of the p5.js website using Node.js, Grunt, YAML and Assemble",
                    "forks": {
                        "totalCount": 11
                    },
                    "id": "MDEwOlJlcG9zaXRvcnkzNzg3Njg4MQ==",
                    "languages": {
                        "edges": [
                            {
                                "node": {
                                    "color": "#f1e05a",
                                    "id": "MDg6TGFuZ3VhZ2UxNDA=",
                                    "name": "JavaScript"
                                },
                                "size": 6225547
                            },
                            {
                                "node": {
                                    "color": "#563d7c",
                                    "id": "MDg6TGFuZ3VhZ2UzMDg=",
                                    "name": "CSS"
                                },
                                "size": 76002
                            },
                            {
                                "node": {
                                    "color": "#e44b23",
                                    "id": "MDg6TGFuZ3VhZ2U0MTc=",
                                    "name": "HTML"
                                },
                                "size": 173771
                            }
                        ]
                    },
                    "primaryLanguage": {
                        "color": "#f1e05a",
                        "name": "JavaScript",
                        "id": "MDg6TGFuZ3VhZ2UxNDA="
                    },
                    "updatedAt": "2017-01-24T17:44:28Z",
                    "watchers": {
                        "totalCount": 7
                    },
                    "stargazers": {
                        "totalCount": 18
                    },
                    "isFork": false,
                    "contribution": -1,
                    "homepageURL": "",
                    "createdAt": "2015-06-22T19:44:26Z",
                    "name": "p5.js-website"
                }
            },
            {
                "node": {
                    "description": "Adaptive Web Components Framework",
                    "forks": {
                        "totalCount": 0
                    },
                    "id": "MDEwOlJlcG9zaXRvcnk2NjI3ODM2Mg==",
                    "languages": {
                        "edges": [
                            {
                                "node": {
                                    "color": "#563d7c",
                                    "id": "MDg6TGFuZ3VhZ2UzMDg=",
                                    "name": "CSS"
                                },
                                "size": 6194
                            },
                            {
                                "node": {
                                    "color": "#f1e05a",
                                    "id": "MDg6TGFuZ3VhZ2UxNDA=",
                                    "name": "JavaScript"
                                },
                                "size": 15431
                            },
                            {
                                "node": {
                                    "color": "#e44b23",
                                    "id": "MDg6TGFuZ3VhZ2U0MTc=",
                                    "name": "HTML"
                                },
                                "size": 27044
                            }
                        ]
                    },
                    "primaryLanguage": {
                        "color": "#e44b23",
                        "name": "HTML",
                        "id": "MDg6TGFuZ3VhZ2U0MTc="
                    },
                    "updatedAt": "2016-12-02T11:01:05Z",
                    "watchers": {
                        "totalCount": 7
                    },
                    "stargazers": {
                        "totalCount": 0
                    },
                    "isFork": false,
                    "contribution": -1,
                    "homepageURL": "http://darwin.gpii.eu",
                    "createdAt": "2016-08-22T14:11:23Z",
                    "name": "AWC"
                }
            },
            {
                "node": {
                    "description": "Contributed library to use the Leap Motion in Processing.",
                    "forks": {
                        "totalCount": 56
                    },
                    "id": "MDEwOlJlcG9zaXRvcnk3OTkzNTM0",
                    "languages": {
                        "edges": [
                            {
                                "node": {
                                    "color": "#b07219",
                                    "id": "MDg6TGFuZ3VhZ2UxNTg=",
                                    "name": "Java"
                                },
                                "size": 107564
                            }
                        ]
                    },
                    "primaryLanguage": {
                        "color": "#b07219",
                        "name": "Java",
                        "id": "MDg6TGFuZ3VhZ2UxNTg="
                    },
                    "updatedAt": "2017-01-28T23:39:48Z",
                    "watchers": {
                        "totalCount": 44
                    },
                    "stargazers": {
                        "totalCount": 205
                    },
                    "isFork": false,
                    "contribution": {
                        "adds": 41410,
                        "total_commits": 118,
                        "num_of_weeks": 39,
                        "dels": 25719
                    },
                    "homepageURL": "https://github.com/nok/leap-motion-processing",
                    "createdAt": "2013-02-03T17:15:34Z",
                    "name": "leap-motion-processing"
                }
            },
            {
                "node": {
                    "description": "Contributed library to use multiple Myo's in Processing.",
                    "forks": {
                        "totalCount": 8
                    },
                    "id": "MDEwOlJlcG9zaXRvcnkyNjIxNDE4Mg==",
                    "languages": {
                        "edges": [
                            {
                                "node": {
                                    "color": "#b07219",
                                    "id": "MDg6TGFuZ3VhZ2UxNTg=",
                                    "name": "Java"
                                },
                                "size": 47032
                            }
                        ]
                    },
                    "primaryLanguage": {
                        "color": "#b07219",
                        "name": "Java",
                        "id": "MDg6TGFuZ3VhZ2UxNTg="
                    },
                    "updatedAt": "2017-01-25T20:11:09Z",
                    "watchers": {
                        "totalCount": 14
                    },
                    "stargazers": {
                        "totalCount": 41
                    },
                    "isFork": false,
                    "contribution": {
                        "adds": 27277,
                        "total_commits": 67,
                        "num_of_weeks": 20,
                        "dels": 12659
                    },
                    "homepageURL": "https://github.com/nok/myo-processing",
                    "createdAt": "2014-11-05T10:14:40Z",
                    "name": "myo-processing"
                }
            },
            {
                "node": {
                    "description": "Implementation of the $1 Unistroke Recognizer, a two-dimensional template based gesture recognition, in CoffeeScript.",
                    "forks": {
                        "totalCount": 4
                    },
                    "id": "MDEwOlJlcG9zaXRvcnk4OTYzMjIx",
                    "languages": {
                        "edges": [
                            {
                                "node": {
                                    "color": "#244776",
                                    "id": "MDg6TGFuZ3VhZ2UxOTU=",
                                    "name": "CoffeeScript"
                                },
                                "size": 14680
                            },
                            {
                                "node": {
                                    "color": "#f1e05a",
                                    "id": "MDg6TGFuZ3VhZ2UxNDA=",
                                    "name": "JavaScript"
                                },
                                "size": 2334
                            }
                        ]
                    },
                    "primaryLanguage": {
                        "color": "#244776",
                        "name": "CoffeeScript",
                        "id": "MDg6TGFuZ3VhZ2UxOTU="
                    },
                    "updatedAt": "2017-02-02T10:02:56Z",
                    "watchers": {
                        "totalCount": 4
                    },
                    "stargazers": {
                        "totalCount": 46
                    },
                    "isFork": false,
                    "contribution": {
                        "adds": 6071,
                        "total_commits": 105,
                        "num_of_weeks": 13,
                        "dels": 4221
                    },
                    "homepageURL": "",
                    "createdAt": "2013-03-22T23:51:45Z",
                    "name": "onedollar-unistroke-coffee"
                }
            },
            {
                "node": {
                    "description": "Transpile trained decision trees from Weka to C, Java or JavaScript.",
                    "forks": {
                        "totalCount": 0
                    },
                    "id": "MDEwOlJlcG9zaXRvcnk3NDkxMjMwMA==",
                    "languages": {
                        "edges": [
                            {
                                "node": {
                                    "color": "#89e051",
                                    "id": "MDg6TGFuZ3VhZ2UxMzk=",
                                    "name": "Shell"
                                },
                                "size": 832
                            },
                            {
                                "node": {
                                    "color": "#3572A5",
                                    "id": "MDg6TGFuZ3VhZ2UxNDU=",
                                    "name": "Python"
                                },
                                "size": 16243
                            }
                        ]
                    },
                    "primaryLanguage": {
                        "color": "#3572A5",
                        "name": "Python",
                        "id": "MDg6TGFuZ3VhZ2UxNDU="
                    },
                    "updatedAt": "2016-12-02T10:53:25Z",
                    "watchers": {
                        "totalCount": 0
                    },
                    "stargazers": {
                        "totalCount": 1
                    },
                    "isFork": false,
                    "contribution": {
                        "adds": 2366,
                        "total_commits": 15,
                        "num_of_weeks": 2,
                        "dels": 1515
                    },
                    "homepageURL": "",
                    "createdAt": "2016-11-27T20:27:32Z",
                    "name": "weka-porter"
                }
            },
            {
                "node": {
                    "description": "BitBar plugin to list all created conda environments and to open a new session with a chosen environment.",
                    "forks": {
                        "totalCount": 0
                    },
                    "id": "MDEwOlJlcG9zaXRvcnk3ODQ4MTIxOQ==",
                    "languages": {
                        "edges": [
                            {
                                "node": {
                                    "color": "#3572A5",
                                    "id": "MDg6TGFuZ3VhZ2UxNDU=",
                                    "name": "Python"
                                },
                                "size": 4092
                            }
                        ]
                    },
                    "primaryLanguage": {
                        "color": "#3572A5",
                        "name": "Python",
                        "id": "MDg6TGFuZ3VhZ2UxNDU="
                    },
                    "updatedAt": "2017-01-10T21:09:13Z",
                    "watchers": {
                        "totalCount": 0
                    },
                    "stargazers": {
                        "totalCount": 0
                    },
                    "isFork": false,
                    "contribution": {
                        "adds": 285,
                        "total_commits": 11,
                        "num_of_weeks": 2,
                        "dels": 69
                    },
                    "homepageURL": "",
                    "createdAt": "2017-01-10T00:13:36Z",
                    "name": "conda-envs"
                }
            },
            {
                "node": {
                    "description": "p5.js is a JS client-side library for creating graphic and interactive experiences, based on the core principles of Processing. http://twitter.com/p5xjs \u2014",
                    "forks": {
                        "totalCount": 683
                    },
                    "id": "MDEwOlJlcG9zaXRvcnk4NDI0MDQw",
                    "languages": {
                        "edges": [
                            {
                                "node": {
                                    "color": "#f1e05a",
                                    "id": "MDg6TGFuZ3VhZ2UxNDA=",
                                    "name": "JavaScript"
                                },
                                "size": 2032854
                            },
                            {
                                "node": {
                                    "color": "#e44b23",
                                    "id": "MDg6TGFuZ3VhZ2U0MTc=",
                                    "name": "HTML"
                                },
                                "size": 92115
                            },
                            {
                                "node": {
                                    "color": "#563d7c",
                                    "id": "MDg6TGFuZ3VhZ2UzMDg=",
                                    "name": "CSS"
                                },
                                "size": 4242
                            },
                            {
                                "node": {
                                    "color": null,
                                    "id": "MDg6TGFuZ3VhZ2U0NTI=",
                                    "name": "GLSL"
                                },
                                "size": 4538
                            }
                        ]
                    },
                    "primaryLanguage": {
                        "color": "#f1e05a",
                        "name": "JavaScript",
                        "id": "MDg6TGFuZ3VhZ2UxNDA="
                    },
                    "updatedAt": "2017-02-07T01:54:32Z",
                    "watchers": {
                        "totalCount": 342
                    },
                    "stargazers": {
                        "totalCount": 5006
                    },
                    "isFork": false,
                    "contribution": -1,
                    "homepageURL": "http://p5js.org/",
                    "createdAt": "2013-02-26T03:14:47Z",
                    "name": "p5.js"
                }
            },
            {
                "node": {
                    "description": "Generate and update magically a table of contents based on the headlines of a parsed markdown file.",
                    "forks": {
                        "totalCount": 30
                    },
                    "id": "MDEwOlJlcG9zaXRvcnkyNjY0MDMwNA==",
                    "languages": {
                        "edges": [
                            {
                                "node": {
                                    "color": "#244776",
                                    "id": "MDg6TGFuZ3VhZ2UxOTU=",
                                    "name": "CoffeeScript"
                                },
                                "size": 6840
                            }
                        ]
                    },
                    "primaryLanguage": {
                        "color": "#244776",
                        "name": "CoffeeScript",
                        "id": "MDg6TGFuZ3VhZ2UxOTU="
                    },
                    "updatedAt": "2017-01-31T10:03:21Z",
                    "watchers": {
                        "totalCount": 5
                    },
                    "stargazers": {
                        "totalCount": 45
                    },
                    "isFork": false,
                    "contribution": {
                        "adds": 592,
                        "total_commits": 23,
                        "num_of_weeks": 8,
                        "dels": 217
                    },
                    "homepageURL": "",
                    "createdAt": "2014-11-14T13:42:50Z",
                    "name": "markdown-toc"
                }
            },
            {
                "node": {
                    "description": "Plugin repository for BitBar",
                    "forks": {
                        "totalCount": 318
                    },
                    "id": "MDEwOlJlcG9zaXRvcnk0OTE0MTE5Nw==",
                    "languages": {
                        "edges": [
                            {
                                "node": {
                                    "color": "#89e051",
                                    "id": "MDg6TGFuZ3VhZ2UxMzk=",
                                    "name": "Shell"
                                },
                                "size": 385752
                            },
                            {
                                "node": {
                                    "color": "#3572A5",
                                    "id": "MDg6TGFuZ3VhZ2UxNDU=",
                                    "name": "Python"
                                },
                                "size": 224550
                            },
                            {
                                "node": {
                                    "color": "#701516",
                                    "id": "MDg6TGFuZ3VhZ2UxNDE=",
                                    "name": "Ruby"
                                },
                                "size": 172754
                            },
                            {
                                "node": {
                                    "color": "#f1e05a",
                                    "id": "MDg6TGFuZ3VhZ2UxNDA=",
                                    "name": "JavaScript"
                                },
                                "size": 109609
                            },
                            {
                                "node": {
                                    "color": "#0298c3",
                                    "id": "MDg6TGFuZ3VhZ2UxNDc=",
                                    "name": "Perl"
                                },
                                "size": 24315
                            },
                            {
                                "node": {
                                    "color": "#4F5D95",
                                    "id": "MDg6TGFuZ3VhZ2UxNTE=",
                                    "name": "PHP"
                                },
                                "size": 72976
                            },
                            {
                                "node": {
                                    "color": "#ffac45",
                                    "id": "MDg6TGFuZ3VhZ2UzNzE=",
                                    "name": "Swift"
                                },
                                "size": 10151
                            },
                            {
                                "node": {
                                    "color": "#3fb68b",
                                    "id": "MDg6TGFuZ3VhZ2UxNjE=",
                                    "name": "Common Lisp"
                                },
                                "size": 569
                            }
                        ]
                    },
                    "primaryLanguage": {
                        "color": "#89e051",
                        "name": "Shell",
                        "id": "MDg6TGFuZ3VhZ2UxMzk="
                    },
                    "updatedAt": "2017-02-06T17:40:50Z",
                    "watchers": {
                        "totalCount": 33
                    },
                    "stargazers": {
                        "totalCount": 610
                    },
                    "isFork": false,
                    "contribution": 0,
                    "homepageURL": "https://getbitbar.com",
                    "createdAt": "2016-01-06T14:52:22Z",
                    "name": "bitbar-plugins"
                }
            },
            {
                "node": {
                    "description": "p5.sound brings the Processing approach to Web Audio and p5.js. Demos:",
                    "forks": {
                        "totalCount": 101
                    },
                    "id": "MDEwOlJlcG9zaXRvcnkyMTcxNDY3Nw==",
                    "languages": {
                        "edges": [
                            {
                                "node": {
                                    "color": "#e44b23",
                                    "id": "MDg6TGFuZ3VhZ2U0MTc=",
                                    "name": "HTML"
                                },
                                "size": 6601
                            },
                            {
                                "node": {
                                    "color": "#f1e05a",
                                    "id": "MDg6TGFuZ3VhZ2UxNDA=",
                                    "name": "JavaScript"
                                },
                                "size": 1806109
                            },
                            {
                                "node": {
                                    "color": "#563d7c",
                                    "id": "MDg6TGFuZ3VhZ2UzMDg=",
                                    "name": "CSS"
                                },
                                "size": 36911
                            }
                        ]
                    },
                    "primaryLanguage": {
                        "color": "#f1e05a",
                        "name": "JavaScript",
                        "id": "MDg6TGFuZ3VhZ2UxNDA="
                    },
                    "updatedAt": "2017-02-04T19:32:18Z",
                    "watchers": {
                        "totalCount": 58
                    },
                    "stargazers": {
                        "totalCount": 199
                    },
                    "isFork": false,
                    "contribution": -1,
                    "homepageURL": "http://p5js.org/reference/#/libraries/p5.sound",
                    "createdAt": "2014-07-11T00:04:58Z",
                    "name": "p5.js-sound"
                }
            },
            {
                "node": {
                    "description": "scikit-learn: machine learning in Python",
                    "forks": {
                        "totalCount": 8792
                    },
                    "id": "MDEwOlJlcG9zaXRvcnk4NDMyMjI=",
                    "languages": {
                        "edges": [
                            {
                                "node": {
                                    "color": "#3572A5",
                                    "id": "MDg6TGFuZ3VhZ2UxNDU=",
                                    "name": "Python"
                                },
                                "size": 6985409
                            },
                            {
                                "node": {
                                    "color": null,
                                    "id": "MDg6TGFuZ3VhZ2UyNjQ=",
                                    "name": "PowerShell"
                                },
                                "size": 17042
                            },
                            {
                                "node": {
                                    "color": "#89e051",
                                    "id": "MDg6TGFuZ3VhZ2UxMzk=",
                                    "name": "Shell"
                                },
                                "size": 19203
                            },
                            {
                                "node": {
                                    "color": "#555555",
                                    "id": "MDg6TGFuZ3VhZ2UxNDk=",
                                    "name": "C"
                                },
                                "size": 451977
                            },
                            {
                                "node": {
                                    "color": "#f34b7d",
                                    "id": "MDg6TGFuZ3VhZ2UxNDI=",
                                    "name": "C++"
                                },
                                "size": 140261
                            },
                            {
                                "node": {
                                    "color": "#427819",
                                    "id": "MDg6TGFuZ3VhZ2U0MDM=",
                                    "name": "Makefile"
                                },
                                "size": 1512
                            },
                            {
                                "node": {
                                    "color": "#C1F12E",
                                    "id": "MDg6TGFuZ3VhZ2U0NjM=",
                                    "name": "Batchfile"
                                },
                                "size": 3366
                            }
                        ]
                    },
                    "primaryLanguage": {
                        "color": "#3572A5",
                        "name": "Python",
                        "id": "MDg6TGFuZ3VhZ2UxNDU="
                    },
                    "updatedAt": "2017-02-07T09:51:01Z",
                    "watchers": {
                        "totalCount": 1565
                    },
                    "stargazers": {
                        "totalCount": 16290
                    },
                    "isFork": false,
                    "contribution": 0,
                    "homepageURL": "http://scikit-learn.org",
                    "createdAt": "2010-08-17T09:43:38Z",
                    "name": "scikit-learn"
                }
            },
            {
                "node": {
                    "description": "Course materials/Homework materials for the FREE MOOC course on \"Creative Applications of Deep Learning w/ Tensorflow\" #CADL",
                    "forks": {
                        "totalCount": 294
                    },
                    "id": "MDEwOlJlcG9zaXRvcnk2Mjc1NjQ5Mw==",
                    "languages": {
                        "edges": [
                            {
                                "node": {
                                    "color": "#DA5B0B",
                                    "id": "MDg6TGFuZ3VhZ2U0ODk=",
                                    "name": "Jupyter Notebook"
                                },
                                "size": 29715583
                            },
                            {
                                "node": {
                                    "color": "#3572A5",
                                    "id": "MDg6TGFuZ3VhZ2UxNDU=",
                                    "name": "Python"
                                },
                                "size": 362771
                            },
                            {
                                "node": {
                                    "color": "#89e051",
                                    "id": "MDg6TGFuZ3VhZ2UxMzk=",
                                    "name": "Shell"
                                },
                                "size": 429
                            }
                        ]
                    },
                    "primaryLanguage": {
                        "color": "#DA5B0B",
                        "name": "Jupyter Notebook",
                        "id": "MDg6TGFuZ3VhZ2U0ODk="
                    },
                    "updatedAt": "2017-02-07T09:46:42Z",
                    "watchers": {
                        "totalCount": 57
                    },
                    "stargazers": {
                        "totalCount": 510
                    },
                    "isFork": false,
                    "contribution": 0,
                    "homepageURL": "https://www.kadenze.com/courses/creative-applications-of-deep-learning-with-tensorflow/info",
                    "createdAt": "2016-07-06T22:07:55Z",
                    "name": "CADL"
                }
            },
            {
                "node": {
                    "description": "The website for p5.js.",
                    "forks": {
                        "totalCount": 93
                    },
                    "id": "MDEwOlJlcG9zaXRvcnkxNTM0OTg4Ng==",
                    "languages": {
                        "edges": [
                            {
                                "node": {
                                    "color": "#4F5D95",
                                    "id": "MDg6TGFuZ3VhZ2UxNTE=",
                                    "name": "PHP"
                                },
                                "size": 125159
                            },
                            {
                                "node": {
                                    "color": "#563d7c",
                                    "id": "MDg6TGFuZ3VhZ2UzMDg=",
                                    "name": "CSS"
                                },
                                "size": 94804
                            },
                            {
                                "node": {
                                    "color": "#e44b23",
                                    "id": "MDg6TGFuZ3VhZ2U0MTc=",
                                    "name": "HTML"
                                },
                                "size": 1092428
                            },
                            {
                                "node": {
                                    "color": "#f1e05a",
                                    "id": "MDg6TGFuZ3VhZ2UxNDA=",
                                    "name": "JavaScript"
                                },
                                "size": 9519535
                            },
                            {
                                "node": {
                                    "color": "#89e051",
                                    "id": "MDg6TGFuZ3VhZ2UxMzk=",
                                    "name": "Shell"
                                },
                                "size": 427
                            }
                        ]
                    },
                    "primaryLanguage": {
                        "color": "#f1e05a",
                        "name": "JavaScript",
                        "id": "MDg6TGFuZ3VhZ2UxNDA="
                    },
                    "updatedAt": "2016-10-30T19:09:46Z",
                    "watchers": {
                        "totalCount": 45
                    },
                    "stargazers": {
                        "totalCount": 63
                    },
                    "isFork": false,
                    "contribution": -1,
                    "homepageURL": "http://p5js.org",
                    "createdAt": "2013-12-20T22:39:55Z",
                    "name": "p5.js-website-OLD"
                }
            },
            {
                "node": {
                    "description": "paul's shell, git, etc config files. also homebrew, migration setup. good stuff. ",
                    "forks": {
                        "totalCount": 911
                    },
                    "id": "MDEwOlJlcG9zaXRvcnkzMjUwMjcx",
                    "languages": {
                        "edges": [
                            {
                                "node": {
                                    "color": "#89e051",
                                    "id": "MDg6TGFuZ3VhZ2UxMzk=",
                                    "name": "Shell"
                                },
                                "size": 60098
                            },
                            {
                                "node": {
                                    "color": "#3572A5",
                                    "id": "MDg6TGFuZ3VhZ2UxNDU=",
                                    "name": "Python"
                                },
                                "size": 4510
                            },
                            {
                                "node": {
                                    "color": "#f1e05a",
                                    "id": "MDg6TGFuZ3VhZ2UxNDA=",
                                    "name": "JavaScript"
                                },
                                "size": 240
                            },
                            {
                                "node": {
                                    "color": "#199f4b",
                                    "id": "MDg6TGFuZ3VhZ2U1Njk=",
                                    "name": "Vim script"
                                },
                                "size": 128916
                            }
                        ]
                    },
                    "primaryLanguage": {
                        "color": "#199f4b",
                        "name": "Vim script",
                        "id": "MDg6TGFuZ3VhZ2U1Njk="
                    },
                    "updatedAt": "2017-02-07T05:24:03Z",
                    "watchers": {
                        "totalCount": 150
                    },
                    "stargazers": {
                        "totalCount": 2512
                    },
                    "isFork": false,
                    "contribution": -1,
                    "homepageURL": "",
                    "createdAt": "2012-01-23T20:50:57Z",
                    "name": "dotfiles"
                }
            },
            {
                "node": {
                    "description": "Functions for generating black and white images using Bill Atkinson's dithering algorithm.",
                    "forks": {
                        "totalCount": 1
                    },
                    "id": "MDEwOlJlcG9zaXRvcnkyNjI4OTU2NQ==",
                    "languages": {
                        "edges": [
                            {
                                "node": {
                                    "color": "#3572A5",
                                    "id": "MDg6TGFuZ3VhZ2UxNDU=",
                                    "name": "Python"
                                },
                                "size": 2846
                            }
                        ]
                    },
                    "primaryLanguage": {
                        "color": "#3572A5",
                        "name": "Python",
                        "id": "MDg6TGFuZ3VhZ2UxNDU="
                    },
                    "updatedAt": "2016-06-06T23:49:33Z",
                    "watchers": {
                        "totalCount": 12
                    },
                    "stargazers": {
                        "totalCount": 1
                    },
                    "isFork": false,
                    "contribution": -1,
                    "homepageURL": "",
                    "createdAt": "2014-11-06T20:53:11Z",
                    "name": "py-cooperhewitt-roboteyes-atkinson"
                }
            },
            {
                "node": {
                    "description": "Processing reference, examples, tutorials, and website",
                    "forks": {
                        "totalCount": 88
                    },
                    "id": "MDEwOlJlcG9zaXRvcnkyMDY2NTM0OQ==",
                    "languages": {
                        "edges": [
                            {
                                "node": {
                                    "color": "#4F5D95",
                                    "id": "MDg6TGFuZ3VhZ2UxNTE=",
                                    "name": "PHP"
                                },
                                "size": 1385724
                            },
                            {
                                "node": {
                                    "color": "#e44b23",
                                    "id": "MDg6TGFuZ3VhZ2U0MTc=",
                                    "name": "HTML"
                                },
                                "size": 1647988
                            },
                            {
                                "node": {
                                    "color": "#0096D8",
                                    "id": "MDg6TGFuZ3VhZ2UzMDE=",
                                    "name": "Processing"
                                },
                                "size": 1526510
                            },
                            {
                                "node": {
                                    "color": null,
                                    "id": "MDg6TGFuZ3VhZ2U0NTI=",
                                    "name": "GLSL"
                                },
                                "size": 33788
                            },
                            {
                                "node": {
                                    "color": "#f1e05a",
                                    "id": "MDg6TGFuZ3VhZ2UxNDA=",
                                    "name": "JavaScript"
                                },
                                "size": 286642
                            },
                            {
                                "node": {
                                    "color": "#b07219",
                                    "id": "MDg6TGFuZ3VhZ2UxNTg=",
                                    "name": "Java"
                                },
                                "size": 186499
                            },
                            {
                                "node": {
                                    "color": "#3572A5",
                                    "id": "MDg6TGFuZ3VhZ2UxNDU=",
                                    "name": "Python"
                                },
                                "size": 23863
                            },
                            {
                                "node": {
                                    "color": "#563d7c",
                                    "id": "MDg6TGFuZ3VhZ2UzMDg=",
                                    "name": "CSS"
                                },
                                "size": 135510
                            },
                            {
                                "node": {
                                    "color": "#89e051",
                                    "id": "MDg6TGFuZ3VhZ2UxMzk=",
                                    "name": "Shell"
                                },
                                "size": 11633
                            },
                            {
                                "node": {
                                    "color": "#0298c3",
                                    "id": "MDg6TGFuZ3VhZ2UxNDc=",
                                    "name": "Perl"
                                },
                                "size": 5339
                            },
                            {
                                "node": {
                                    "color": "#bd79d1",
                                    "id": "MDg6TGFuZ3VhZ2UyNTY=",
                                    "name": "Arduino"
                                },
                                "size": 348
                            }
                        ]
                    },
                    "primaryLanguage": {
                        "color": "#e44b23",
                        "name": "HTML",
                        "id": "MDg6TGFuZ3VhZ2U0MTc="
                    },
                    "updatedAt": "2017-02-03T01:07:30Z",
                    "watchers": {
                        "totalCount": 58
                    },
                    "stargazers": {
                        "totalCount": 192
                    },
                    "isFork": false,
                    "contribution": -1,
                    "homepageURL": "http://processing.org",
                    "createdAt": "2014-06-09T23:10:25Z",
                    "name": "processing-docs"
                }
            },
            {
                "node": {
                    "description": "Fantastic Micro-Frameworks and Micro-Libraries for Fun and Profit!",
                    "forks": {
                        "totalCount": 574
                    },
                    "id": "MDEwOlJlcG9zaXRvcnkxNjgwMzM2",
                    "languages": {
                        "edges": [
                            {
                                "node": {
                                    "color": "#427819",
                                    "id": "MDg6TGFuZ3VhZ2U0MDM=",
                                    "name": "Makefile"
                                },
                                "size": 347
                            },
                            {
                                "node": {
                                    "color": "#f1e05a",
                                    "id": "MDg6TGFuZ3VhZ2UxNDA=",
                                    "name": "JavaScript"
                                },
                                "size": 251684
                            },
                            {
                                "node": {
                                    "color": "#e44b23",
                                    "id": "MDg6TGFuZ3VhZ2U0MTc=",
                                    "name": "HTML"
                                },
                                "size": 18447
                            },
                            {
                                "node": {
                                    "color": "#563d7c",
                                    "id": "MDg6TGFuZ3VhZ2UzMDg=",
                                    "name": "CSS"
                                },
                                "size": 23823
                            }
                        ]
                    },
                    "primaryLanguage": {
                        "color": "#f1e05a",
                        "name": "JavaScript",
                        "id": "MDg6TGFuZ3VhZ2UxNDA="
                    },
                    "updatedAt": "2017-01-30T19:40:53Z",
                    "watchers": {
                        "totalCount": 71
                    },
                    "stargazers": {
                        "totalCount": 1447
                    },
                    "isFork": false,
                    "contribution": -1,
                    "homepageURL": "http://microjs.com/",
                    "createdAt": "2011-04-29T11:17:41Z",
                    "name": "microjs.com"
                }
            },
            {
                "node": {
                    "description": "Small collection of my written command line helpers.",
                    "forks": {
                        "totalCount": 0
                    },
                    "id": "MDEwOlJlcG9zaXRvcnk3OTA2NDI5OA==",
                    "languages": {
                        "edges": [
                            {
                                "node": {
                                    "color": "#89e051",
                                    "id": "MDg6TGFuZ3VhZ2UxMzk=",
                                    "name": "Shell"
                                },
                                "size": 346
                            }
                        ]
                    },
                    "primaryLanguage": {
                        "color": "#89e051",
                        "name": "Shell",
                        "id": "MDg6TGFuZ3VhZ2UxMzk="
                    },
                    "updatedAt": "2017-01-18T16:31:14Z",
                    "watchers": {
                        "totalCount": 0
                    },
                    "stargazers": {
                        "totalCount": 1
                    },
                    "isFork": false,
                    "contribution": {
                        "adds": 48,
                        "total_commits": 1,
                        "num_of_weeks": 1,
                        "dels": 0
                    },
                    "homepageURL": null,
                    "createdAt": "2017-01-15T22:39:31Z",
                    "name": "bash-recipes"
                }
            },
            {
                "node": {
                    "description": ":globe_with_meridians: Online and offline resources for learning foreign languages",
                    "forks": {
                        "totalCount": 1
                    },
                    "id": "MDEwOlJlcG9zaXRvcnk0MDc3MDAzOQ==",
                    "languages": {
                        "edges": [
                            {
                                "node": {
                                    "color": "#e44b23",
                                    "id": "MDg6TGFuZ3VhZ2U0MTc=",
                                    "name": "HTML"
                                },
                                "size": 1851072
                            },
                            {
                                "node": {
                                    "color": "#563d7c",
                                    "id": "MDg6TGFuZ3VhZ2UzMDg=",
                                    "name": "CSS"
                                },
                                "size": 17441
                            }
                        ]
                    },
                    "primaryLanguage": {
                        "color": "#e44b23",
                        "name": "HTML",
                        "id": "MDg6TGFuZ3VhZ2U0MTc="
                    },
                    "updatedAt": "2016-12-19T21:22:15Z",
                    "watchers": {
                        "totalCount": 1
                    },
                    "stargazers": {
                        "totalCount": 2
                    },
                    "isFork": false,
                    "contribution": -1,
                    "homepageURL": "http://cstrobbe.github.io/languagelearning/",
                    "createdAt": "2015-08-15T16:13:15Z",
                    "name": "languagelearning"
                }
            },
            {
                "node": {
                    "description": "Settings-based personalization framework",
                    "forks": {
                        "totalCount": 0
                    },
                    "id": "MDEwOlJlcG9zaXRvcnk3MDE0NzA1MA==",
                    "languages": {
                        "edges": [
                            {
                                "node": {
                                    "color": "#b07219",
                                    "id": "MDg6TGFuZ3VhZ2UxNTg=",
                                    "name": "Java"
                                },
                                "size": 9474
                            },
                            {
                                "node": {
                                    "color": "#e44b23",
                                    "id": "MDg6TGFuZ3VhZ2U0MTc=",
                                    "name": "HTML"
                                },
                                "size": 110
                            }
                        ]
                    },
                    "primaryLanguage": {
                        "color": "#b07219",
                        "name": "Java",
                        "id": "MDg6TGFuZ3VhZ2UxNTg="
                    },
                    "updatedAt": "2016-12-02T10:58:22Z",
                    "watchers": {
                        "totalCount": 5
                    },
                    "stargazers": {
                        "totalCount": 1
                    },
                    "isFork": false,
                    "contribution": -1,
                    "homepageURL": "",
                    "createdAt": "2016-10-06T11:18:02Z",
                    "name": "OpenAPE"
                }
            }
        ],
        "pageInfo": {
            "hasNextPage": false,
            "endCursor": "MjM="
        }
    },
    "bio": "Juggle w/ data.",
    "gists": {
        "totalCount": 23
    },
    "name": "Darius Morawiec",
    "id": "MDQ6VXNlcjY3MDY0MQ=="
}