{
    "organizations": {
        "totalCount": 0,
        "nodes": []
    },
    "location": "Berlin, Germany",
    "email": "nickrjensen@gmail.com",
    "pullRequests": {
        "totalCount": 4
    },
    "company": "",
    "pinnedRepositories": {
        "totalCount": 0,
        "nodes": []
    },
    "websiteURL": "https://nrj.io",
    "watching": {
        "totalCount": 45
    },
    "avatarURL": "https://avatars2.githubusercontent.com/u/149472?v=3",
    "starredRepositories": {
        "totalCount": 22
    },
    "followers": {
        "totalCount": 132
    },
    "login": "nrj",
    "following": {
        "totalCount": 7
    },
    "contributedRepositories": {
        "totalCount": 2,
        "edges": [
            {
                "node": {
                    "description": "Official C# support for Visual Studio Code (powered by OmniSharp)",
                    "forks": {
                        "totalCount": 121
                    },
                    "id": "MDEwOlJlcG9zaXRvcnk0NzM0MTk2MQ==",
                    "languages": {
                        "edges": [
                            {
                                "node": {
                                    "color": "#f1e05a",
                                    "id": "MDg6TGFuZ3VhZ2UxNDA=",
                                    "name": "JavaScript"
                                },
                                "size": 5815
                            },
                            {
                                "node": {
                                    "color": "#2b7489",
                                    "id": "MDg6TGFuZ3VhZ2UyODc=",
                                    "name": "TypeScript"
                                },
                                "size": 274106
                            }
                        ]
                    },
                    "primaryLanguage": {
                        "color": "#2b7489",
                        "name": "TypeScript",
                        "id": "MDg6TGFuZ3VhZ2UyODc="
                    },
                    "updatedAt": "2017-02-07T08:51:24Z",
                    "watchers": {
                        "totalCount": 222
                    },
                    "stargazers": {
                        "totalCount": 371
                    },
                    "isFork": false,
                    "contribution": -1,
                    "homepageURL": "",
                    "createdAt": "2015-12-03T15:45:21Z",
                    "name": "omnisharp-vscode"
                }
            },
            {
                "node": {
                    "description": "Docker-based SNI proxy for watching U.S. Netflix, Hulu, MTV, Vevo, Crackle, ABC, NBC, PBS...",
                    "forks": {
                        "totalCount": 36
                    },
                    "id": "MDEwOlJlcG9zaXRvcnkzNTMwMDAzNg==",
                    "languages": {
                        "edges": [
                            {
                                "node": {
                                    "color": "#89e051",
                                    "id": "MDg6TGFuZ3VhZ2UxMzk=",
                                    "name": "Shell"
                                },
                                "size": 68
                            },
                            {
                                "node": {
                                    "color": "#3572A5",
                                    "id": "MDg6TGFuZ3VhZ2UxNDU=",
                                    "name": "Python"
                                },
                                "size": 2351
                            }
                        ]
                    },
                    "primaryLanguage": {
                        "color": "#3572A5",
                        "name": "Python",
                        "id": "MDg6TGFuZ3VhZ2UxNDU="
                    },
                    "updatedAt": "2017-02-07T06:49:25Z",
                    "watchers": {
                        "totalCount": 40
                    },
                    "stargazers": {
                        "totalCount": 281
                    },
                    "isFork": false,
                    "contribution": -1,
                    "homepageURL": "",
                    "createdAt": "2015-05-08T20:20:46Z",
                    "name": "dockerflix"
                }
            }
        ],
        "pageInfo": {
            "hasNextPage": false,
            "endCursor": "Mg=="
        }
    },
    "bio": null,
    "gists": {
        "totalCount": 11
    },
    "name": "Nick Jensen",
    "id": "MDQ6VXNlcjE0OTQ3Mg=="
}